LICENSE
README.rst
requirements.txt
setup.py
pfmongo/__init__.py
pfmongo/__main__.py
pfmongo/app_core.py
pfmongo/driver.py
pfmongo/env.py
pfmongo/pfmongo.py
pfmongo/smashes.py
pfmongo.egg-info/PKG-INFO
pfmongo.egg-info/SOURCES.txt
pfmongo.egg-info/dependency_links.txt
pfmongo.egg-info/entry_points.txt
pfmongo.egg-info/not-zip-safe
pfmongo.egg-info/requires.txt
pfmongo.egg-info/top_level.txt
pfmongo/commands/__init__.py
pfmongo/commands/collection.py
pfmongo/commands/database.py
pfmongo/commands/document.py
pfmongo/commands/fs.py
pfmongo/commands/man.py
pfmongo/commands/smash.py
pfmongo/commands/state.py
pfmongo/commands/clop/connect.py
pfmongo/commands/clop/deleteCol.py
pfmongo/commands/clop/showAll.py
pfmongo/commands/dbop/connect.py
pfmongo/commands/dbop/deleteDB.py
pfmongo/commands/dbop/showAll.py
pfmongo/commands/docop/add.py
pfmongo/commands/docop/delete.py
pfmongo/commands/docop/get.py
pfmongo/commands/docop/search.py
pfmongo/commands/docop/showAll.py
pfmongo/commands/fop/__init__.py
pfmongo/commands/fop/cat.py
pfmongo/commands/fop/cd.py
pfmongo/commands/fop/exp.py
pfmongo/commands/fop/imp.py
pfmongo/commands/fop/ls.py
pfmongo/commands/fop/mkcd.py
pfmongo/commands/fop/prompt.py
pfmongo/commands/fop/pwd.py
pfmongo/commands/fop/rm.py
pfmongo/commands/fop/sg.py
pfmongo/commands/slib/completion.py
pfmongo/commands/slib/t2.py
pfmongo/commands/slib/tabc.py
pfmongo/commands/slib/tabcomplete.py
pfmongo/commands/slib/tabcomplete2.py
pfmongo/commands/stateop/showAll.py
pfmongo/config/__init__.py
pfmongo/config/settings.py
pfmongo/db/pfdb.py
pfmongo/models/dataModel.py
pfmongo/models/fsModel.py
pfmongo/models/responseModel.py
tests/test_ahash.py
tests/test_collection.py
tests/test_core.py
tests/test_database.py
tests/test_document.py
tests/test_smash.py