Metadata-Version: 2.1
Name: pfmongo
Version: 0.9.900
Summary: A mongodb (portable) "pf" client
Home-page: https://github.com/FNNDSC/pfmongo
Author: FNNDSC
Author-email: dev@babymri.org
License: MIT
License-File: LICENSE
Requires-Dist: aiohttp
Requires-Dist: pudb
Requires-Dist: ipython
Requires-Dist: pytest
Requires-Dist: pytest-asyncio
Requires-Dist: motor
Requires-Dist: dnspython
Requires-Dist: loguru
Requires-Dist: pfmisc
Requires-Dist: pydantic>=2.3.0
Requires-Dist: pydantic_settings
Requires-Dist: click
Requires-Dist: appdirs
Requires-Dist: tabulate
Requires-Dist: fortune-python
Requires-Dist: fontawesome
Requires-Dist: rich
Requires-Dist: legacy-cgi
